[
    {
        "Alphabet": "A",
        "Alphabet Phonetics ": "Alpha"
    },
    {
        "Alphabet": "B",
        "Alphabet Phonetics ": "Bravo"
    },
    {
        "Alphabet": "C",
        "Alphabet Phonetics ": "Charlie"
    },
    {
        "Alphabet": "D",
        "Alphabet Phonetics ": "Delta"
    },
    {
        "Alphabet": "E",
        "Alphabet Phonetics ": "Echo"
    },
    {
        "Alphabet": "F",
        "Alphabet Phonetics ": "Foxtrot"
    },
    {
        "Alphabet": "G",
        "Alphabet Phonetics ": "Golf"
    },
    {
        "Alphabet": "H",
        "Alphabet Phonetics ": "Hotel"
    },
    {
        "Alphabet": "I",
        "Alphabet Phonetics ": "India"
    },
    {
        "Alphabet": "J",
        "Alphabet Phonetics ": "Juliet"
    },
    {
        "Alphabet": "K",
        "Alphabet Phonetics ": "Kilo"
    },
    {
        "Alphabet": "L",
        "Alphabet Phonetics ": "Lima"
    },
    {
        "Alphabet": "M",
        "Alphabet Phonetics ": "Mike"
    },
    {
        "Alphabet": "N",
        "Alphabet Phonetics ": "November"
    },
    {
        "Alphabet": "O",
        "Alphabet Phonetics ": "Oscar"
    },
    {
        "Alphabet": "P",
        "Alphabet Phonetics ": "Papa"
    },
    {
        "Alphabet": "Q",
        "Alphabet Phonetics ": "Quebec"
    },
    {
        "Alphabet": "R",
        "Alphabet Phonetics ": "Romeo"
    },
    {
        "Alphabet": "S",
        "Alphabet Phonetics ": "Sierra"
    },
    {
        "Alphabet": "T",
        "Alphabet Phonetics ": "Tango"
    },
    {
        "Alphabet": "U",
        "Alphabet Phonetics ": "Uniform"
    },
    {
        "Alphabet": "V",
        "Alphabet Phonetics ": "Victor"
    },
    {
        "Alphabet": "W",
        "Alphabet Phonetics ": "Whiskey"
    },
    {
        "Alphabet": "X",
        "Alphabet Phonetics ": "X-ray"
    },
    {
        "Alphabet": "Y",
        "Alphabet Phonetics ": "Yankee"
    },
    {
        "Alphabet": "Z",
        "Alphabet Phonetics ": "Zulu"
    }
]